Metadata-Version: 1.1
Name: bitfinex
Version: 0.2.2
Summary: Python client for the Bitfinex API
Home-page: https://github.com/scottjbarr/bitfinex
Author: Scott Barr
Author-email: scottjbarr@gmail.com
License: MIT
Download-URL: https://github.com/scottjbarr/bitfinex/tarball/0.2.2
Keywords: bitcoin,btc
Platform: UNKNOWN
